<?xml version="1.0" encoding="UTF-8"?>
<MRPKSData version="2.0" countryCode="CZ" currencyCode="CZK">
    <!--Source AppVendor="MRP" AppName="MRP-K/S" AppVersion="5.92(001)" AppSerial="UC010001"-->
    <IssuedInvoices>
        <Invoice>
            <DocumentNumber>2018023</DocumentNumber>
            <IssueDate>2018-12-28</IssueDate>
            <CurrencyCode>CZK</CurrencyCode>
            <ValuesWithTax>F</ValuesWithTax>
            <TaxCode>41</TaxCode>
            <ZeroTaxRateAmount>0.00</ZeroTaxRateAmount>
            <ReducedTaxRateAmount>0.00</ReducedTaxRateAmount>
            <BaseTaxRateAmount>10000.00</BaseTaxRateAmount>
            <RoundingAmount>0.00</RoundingAmount>
            <ReducedTaxRateTax>0.00</ReducedTaxRateTax>
            <BaseTaxRateTax>2100.00</BaseTaxRateTax>
            <TotalWithTaxCurr>0.00</TotalWithTaxCurr>
            <TaxPointDate>2018-12-28</TaxPointDate>
            <DoubleEntryBookkeepingCode>0.000</DoubleEntryBookkeepingCode>
            <SingleEntryBookkeepingCode>0</SingleEntryBookkeepingCode>
            <SingleEntryBookkeepingSubCode>0</SingleEntryBookkeepingSubCode>
            <ControlStatement_Leasing>F</ControlStatement_Leasing>
            <TotalWeight>0.000000</TotalWeight>
            <CostCentre>03</CostCentre>
            <ContractNumber>0</ContractNumber>
            <VatRegime>0</VatRegime>
            <VatCountry>CZ</VatCountry>
            <EURExchangeRate>1.000000</EURExchangeRate>
            <EURExchangeRateAmount>1.000000</EURExchangeRateAmount>
            <CalcParams>UPDP=2;VATRU=0.10;VATRM=0;TRU=1.00;TRM=0;VATCA=1;VATCUPA=1;TRD=0;TRDCA=0;VATFRB=0</CalcParams>
            <VariableSymbol>2018023</VariableSymbol>
            <ConstantSymbol>0308</ConstantSymbol>
            <PaymentDueDate>2019-01-11</PaymentDueDate>
            <CurrRateAmount>1.000000</CurrRateAmount>
            <CurrRate>1.000000</CurrRate>
            <PaidAmount>12100.00</PaidAmount>
            <PaidAmountCurr>12100.00</PaidAmountCurr>
            <InvoiceType>F</InvoiceType>
            <PaymentMeansCode>převodem</PaymentMeansCode>
            <Discount>0.00</Discount>
            <Company>
                <CompanyId>99999991</CompanyId>
                <Name>Spořitelní dům a.s.</Name>
                <Street>U Spořitelny 5</Street>
                <City>Brno 100</City>
                <CountryCode>CZ</CountryCode>
                <ZipCode>60010</ZipCode>
                <VatNumber>CZ99999991</VatNumber>
                <NaturalPerson>F</NaturalPerson>
            </Company>
            <Items>
                <Item>
                    <Description>Pronájem reklamní plochy</Description>
                    <RowType>1</RowType>
                    <TaxCode>41</TaxCode>
                    <Quantity>1.000000</Quantity>
                    <UnitPrice>10000.000000</UnitPrice>
                    <TaxPercent>21.00</TaxPercent>
                    <TaxAmount>2100.000000</TaxAmount>
                    <DiscountPercent>0.00</DiscountPercent>
                    <UnitDiscount>0.000000</UnitDiscount>
                    <StockCardNumber>0.00</StockCardNumber>
                    <CostCentre>03</CostCentre>
                    <ContractNumber>0</ContractNumber>
                    <RowSumType>1</RowSumType>
                    <TotalWeight>0.000000</TotalWeight>
                </Item>
                <Item>
                    <Description>.</Description>
                    <RowType>1</RowType>
                    <TaxCode>41</TaxCode>
                    <Quantity>0.000000</Quantity>
                    <UnitPrice>0.000000</UnitPrice>
                    <TaxPercent>0.00</TaxPercent>
                    <TaxAmount>0.000000</TaxAmount>
                    <DiscountPercent>0.00</DiscountPercent>
                    <UnitDiscount>0.000000</UnitDiscount>
                    <StockCardNumber>0.00</StockCardNumber>
                    <CostCentre>03</CostCentre>
                    <ContractNumber>0</ContractNumber>
                    <RowSumType>1</RowSumType>
                    <TotalWeight>0.000000</TotalWeight>
                </Item>
                <Item>
                    <Description>.</Description>
                    <RowType>1</RowType>
                    <TaxCode>41</TaxCode>
                    <Quantity>0.000000</Quantity>
                    <UnitPrice>0.000000</UnitPrice>
                    <TaxPercent>0.00</TaxPercent>
                    <TaxAmount>0.000000</TaxAmount>
                    <DiscountPercent>0.00</DiscountPercent>
                    <UnitDiscount>0.000000</UnitDiscount>
                    <StockCardNumber>0.00</StockCardNumber>
                    <CostCentre>03</CostCentre>
                    <ContractNumber>0</ContractNumber>
                    <RowSumType>1</RowSumType>
                    <TotalWeight>0.000000</TotalWeight>
                </Item>
                <Item>
                    <Description>---------- Tuzemská faktura  ------</Description>
                    <RowType>1</RowType>
                    <TaxCode>41</TaxCode>
                    <Quantity>0.000000</Quantity>
                    <UnitPrice>0.000000</UnitPrice>
                    <TaxPercent>0.00</TaxPercent>
                    <TaxAmount>0.000000</TaxAmount>
                    <DiscountPercent>0.00</DiscountPercent>
                    <UnitDiscount>0.000000</UnitDiscount>
                    <StockCardNumber>0.00</StockCardNumber>
                    <CostCentre>03</CostCentre>
                    <ContractNumber>0</ContractNumber>
                    <RowSumType>1</RowSumType>
                    <TotalWeight>0.000000</TotalWeight>
                </Item>
            </Items>
            <SumValues>
                <SumValue>
                    <TaxCode>41</TaxCode>
                    <TaxType>1</TaxType>
                    <TaxPercent>21.00</TaxPercent>
                    <CurrencyCode>CZK</CurrencyCode>
                    <Amount>10000.00</Amount>
                    <Tax>2100.00</Tax>
                    <TaxCurrRateAmount>0.00</TaxCurrRateAmount>
                    <TaxCurrRateTax>0.00</TaxCurrRateTax>
                    <ReverseChargeAmount>0.00</ReverseChargeAmount>
                    <ReverseChargeTax>0.00</ReverseChargeTax>
                    <TaxCurrRateReverseChargeAmount>0.00</TaxCurrRateReverseChargeAmount>
                    <TaxCurrRateReverseChargeTax>0.00</TaxCurrRateReverseChargeTax>
                    <TaxApplied>0.00</TaxApplied>
                </SumValue>
                <SumValue>
                    <TaxCode>41</TaxCode>
                    <TaxType>3</TaxType>
                    <TaxPercent>0.00</TaxPercent>
                    <CurrencyCode>CZK</CurrencyCode>
                    <Amount>0.00</Amount>
                    <Tax>0.00</Tax>
                    <TaxCurrRateAmount>0.00</TaxCurrRateAmount>
                    <TaxCurrRateTax>0.00</TaxCurrRateTax>
                    <ReverseChargeAmount>0.00</ReverseChargeAmount>
                    <ReverseChargeTax>0.00</ReverseChargeTax>
                    <TaxCurrRateReverseChargeAmount>0.00</TaxCurrRateReverseChargeAmount>
                    <TaxCurrRateReverseChargeTax>0.00</TaxCurrRateReverseChargeTax>
                    <TaxApplied>0.00</TaxApplied>
                </SumValue>
            </SumValues>
            <Payments>
                <Payment>
                    <PaymentType>1</PaymentType>
                    <PaymentDate>2019-01-15</PaymentDate>
                    <DocumentNumber>BV1900001</DocumentNumber>
                    <Amount>12100.00</Amount>
                    <AmountCurr>12100.00</AmountCurr>
                    <AmountPaidDocumentCurr>12100.00</AmountPaidDocumentCurr>
                    <CurrencyCode>CZK</CurrencyCode>
                    <CurrRate>1.000000</CurrRate>
                    <CurrRateAmount>1.000000</CurrRateAmount>
                </Payment>
            </Payments>
        </Invoice>
        <Invoice>
            <DocumentNumber>2019001</DocumentNumber>
            <IssueDate>2019-01-15</IssueDate>
            <CurrencyCode>CZK</CurrencyCode>
            <ValuesWithTax>F</ValuesWithTax>
            <TaxCode>41</TaxCode>
            <ZeroTaxRateAmount>0.00</ZeroTaxRateAmount>
            <ReducedTaxRateAmount>0.00</ReducedTaxRateAmount>
            <BaseTaxRateAmount>29632.00</BaseTaxRateAmount>
            <RoundingAmount>0.30</RoundingAmount>
            <ReducedTaxRateTax>0.00</ReducedTaxRateTax>
            <BaseTaxRateTax>6222.70</BaseTaxRateTax>
            <TotalWithTaxCurr>0.00</TotalWithTaxCurr>
            <TaxPointDate>2019-01-15</TaxPointDate>
            <DoubleEntryBookkeepingCode>0.000</DoubleEntryBookkeepingCode>
            <SingleEntryBookkeepingCode>0</SingleEntryBookkeepingCode>
            <SingleEntryBookkeepingSubCode>0</SingleEntryBookkeepingSubCode>
            <ControlStatement_Leasing>F</ControlStatement_Leasing>
            <TotalWeight>140.000000</TotalWeight>
            <CostCentre>03</CostCentre>
            <ContractNumber>0</ContractNumber>
            <VatRegime>0</VatRegime>
            <VatCountry>CZ</VatCountry>
            <EURExchangeRate>1.000000</EURExchangeRate>
            <EURExchangeRateAmount>1.000000</EURExchangeRateAmount>
            <CalcParams>UPDP=2;VATRU=0.10;VATRM=0;TRU=1.00;TRM=0;VATCA=1;VATCUPA=1;TRD=0;TRDCA=0;VATFRB=0</CalcParams>
            <VariableSymbol>2019001</VariableSymbol>
            <ConstantSymbol>0308</ConstantSymbol>
            <PaymentDueDate>2019-01-29</PaymentDueDate>
            <CurrRateAmount>1.000000</CurrRateAmount>
            <CurrRate>1.000000</CurrRate>
            <PaidAmount>35855.00</PaidAmount>
            <PaidAmountCurr>35855.00</PaidAmountCurr>
            <InvoiceType>F</InvoiceType>
            <DeliveryNoteID>V190001</DeliveryNoteID>
            <PaymentMeansCode>převodem</PaymentMeansCode>
            <DeliveryTypeCode>PPL</DeliveryTypeCode>
            <OrderNumber>OP19001</OrderNumber>
            <OrderDate>2019-01-15</OrderDate>
            <Discount>0.00</Discount>
            <Company>
                <CompanyId>99999991</CompanyId>
                <Name>Spořitelní dům a.s.</Name>
                <Street>U Spořitelny 5</Street>
                <City>Brno 100</City>
                <CountryCode>CZ</CountryCode>
                <ZipCode>60010</ZipCode>
                <VatNumber>CZ99999991</VatNumber>
                <NaturalPerson>F</NaturalPerson>
            </Company>
            <Items>
                <Item>
                    <Description>1,00 stůl dřevěný</Description>
                    <RowType>1</RowType>
                    <TaxCode>41</TaxCode>
                    <UnitCode>ks</UnitCode>
                    <Quantity>4.000000</Quantity>
                    <UnitPrice>5500.000000</UnitPrice>
                    <TaxPercent>21.00</TaxPercent>
                    <TaxAmount>1155.000000</TaxAmount>
                    <DiscountPercent>0.00</DiscountPercent>
                    <UnitDiscount>0.000000</UnitDiscount>
                    <StockCardNumber>1.00</StockCardNumber>
                    <CostCentre>03</CostCentre>
                    <ContractNumber>0</ContractNumber>
                    <RowSumType>1</RowSumType>
                    <TotalWeight>25.000000</TotalWeight>
                </Item>
                <Item>
                    <Description>4,00 židle  čalouněná</Description>
                    <RowType>1</RowType>
                    <TaxCode>41</TaxCode>
                    <UnitCode>ks</UnitCode>
                    <Quantity>8.000000</Quantity>
                    <UnitPrice>954.000000</UnitPrice>
                    <TaxPercent>21.00</TaxPercent>
                    <TaxAmount>200.340000</TaxAmount>
                    <DiscountPercent>0.00</DiscountPercent>
                    <UnitDiscount>0.000000</UnitDiscount>
                    <StockCardNumber>4.00</StockCardNumber>
                    <CostCentre>03</CostCentre>
                    <ContractNumber>0</ContractNumber>
                    <RowSumType>1</RowSumType>
                    <TotalWeight>5.000000</TotalWeight>
                </Item>
                <Item>
                    <Description>.</Description>
                    <RowType>1</RowType>
                    <TaxCode>41</TaxCode>
                    <Quantity>0.000000</Quantity>
                    <UnitPrice>0.000000</UnitPrice>
                    <TaxPercent>0.00</TaxPercent>
                    <TaxAmount>0.000000</TaxAmount>
                    <DiscountPercent>0.00</DiscountPercent>
                    <UnitDiscount>0.000000</UnitDiscount>
                    <StockCardNumber>0.00</StockCardNumber>
                    <CostCentre>03</CostCentre>
                    <ContractNumber>0</ContractNumber>
                    <RowSumType>1</RowSumType>
                    <TotalWeight>0.000000</TotalWeight>
                </Item>
                <Item>
                    <Description>.</Description>
                    <RowType>1</RowType>
                    <TaxCode>41</TaxCode>
                    <Quantity>0.000000</Quantity>
                    <UnitPrice>0.000000</UnitPrice>
                    <TaxPercent>0.00</TaxPercent>
                    <TaxAmount>0.000000</TaxAmount>
                    <DiscountPercent>0.00</DiscountPercent>
                    <UnitDiscount>0.000000</UnitDiscount>
                    <StockCardNumber>0.00</StockCardNumber>
                    <CostCentre>03</CostCentre>
                    <ContractNumber>0</ContractNumber>
                    <RowSumType>1</RowSumType>
                    <TotalWeight>0.000000</TotalWeight>
                </Item>
                <Item>
                    <Description>------ Tuzemská faktura ------</Description>
                    <RowType>1</RowType>
                    <TaxCode>41</TaxCode>
                    <Quantity>0.000000</Quantity>
                    <UnitPrice>0.000000</UnitPrice>
                    <TaxPercent>0.00</TaxPercent>
                    <TaxAmount>0.000000</TaxAmount>
                    <DiscountPercent>0.00</DiscountPercent>
                    <UnitDiscount>0.000000</UnitDiscount>
                    <StockCardNumber>0.00</StockCardNumber>
                    <CostCentre>03</CostCentre>
                    <ContractNumber>0</ContractNumber>
                    <RowSumType>1</RowSumType>
                    <TotalWeight>0.000000</TotalWeight>
                </Item>
            </Items>
            <SumValues>
                <SumValue>
                    <TaxCode>41</TaxCode>
                    <TaxType>1</TaxType>
                    <TaxPercent>21.00</TaxPercent>
                    <CurrencyCode>CZK</CurrencyCode>
                    <Amount>29632.00</Amount>
                    <Tax>6222.70</Tax>
                    <TaxCurrRateAmount>0.00</TaxCurrRateAmount>
                    <TaxCurrRateTax>0.00</TaxCurrRateTax>
                    <ReverseChargeAmount>0.00</ReverseChargeAmount>
                    <ReverseChargeTax>0.00</ReverseChargeTax>
                    <TaxCurrRateReverseChargeAmount>0.00</TaxCurrRateReverseChargeAmount>
                    <TaxCurrRateReverseChargeTax>0.00</TaxCurrRateReverseChargeTax>
                    <TaxApplied>0.00</TaxApplied>
                </SumValue>
                <SumValue>
                    <TaxCode>41</TaxCode>
                    <TaxType>3</TaxType>
                    <TaxPercent>0.00</TaxPercent>
                    <CurrencyCode>CZK</CurrencyCode>
                    <Amount>0.00</Amount>
                    <Tax>0.00</Tax>
                    <TaxCurrRateAmount>0.00</TaxCurrRateAmount>
                    <TaxCurrRateTax>0.00</TaxCurrRateTax>
                    <ReverseChargeAmount>0.00</ReverseChargeAmount>
                    <ReverseChargeTax>0.00</ReverseChargeTax>
                    <TaxCurrRateReverseChargeAmount>0.00</TaxCurrRateReverseChargeAmount>
                    <TaxCurrRateReverseChargeTax>0.00</TaxCurrRateReverseChargeTax>
                    <TaxApplied>0.00</TaxApplied>
                </SumValue>
                <SumValue>
                    <TaxCode>41</TaxCode>
                    <TaxType>4</TaxType>
                    <TaxPercent>99.00</TaxPercent>
                    <CurrencyCode>CZK</CurrencyCode>
                    <Amount>0.30</Amount>
                    <Tax>0.00</Tax>
                    <TaxCurrRateAmount>0.00</TaxCurrRateAmount>
                    <TaxCurrRateTax>0.00</TaxCurrRateTax>
                    <ReverseChargeAmount>0.00</ReverseChargeAmount>
                    <ReverseChargeTax>0.00</ReverseChargeTax>
                    <TaxCurrRateReverseChargeAmount>0.00</TaxCurrRateReverseChargeAmount>
                    <TaxCurrRateReverseChargeTax>0.00</TaxCurrRateReverseChargeTax>
                    <TaxApplied>0.00</TaxApplied>
                </SumValue>
            </SumValues>
            <Payments>
                <Payment>
                    <PaymentType>1</PaymentType>
                    <PaymentDate>2019-01-15</PaymentDate>
                    <DocumentNumber>BV1900001</DocumentNumber>
                    <Amount>35855.00</Amount>
                    <AmountCurr>35855.00</AmountCurr>
                    <AmountPaidDocumentCurr>35855.00</AmountPaidDocumentCurr>
                    <CurrencyCode>CZK</CurrencyCode>
                    <CurrRate>1.000000</CurrRate>
                    <CurrRateAmount>1.000000</CurrRateAmount>
                </Payment>
            </Payments>
        </Invoice>
        <Invoice>
            <DocumentNumber>2019002</DocumentNumber>
            <IssueDate>2019-01-15</IssueDate>
            <CurrencyCode>CZK</CurrencyCode>
            <ValuesWithTax>F</ValuesWithTax>
            <TaxCode>41</TaxCode>
            <ZeroTaxRateAmount>0.00</ZeroTaxRateAmount>
            <ReducedTaxRateAmount>0.00</ReducedTaxRateAmount>
            <BaseTaxRateAmount>3750.00</BaseTaxRateAmount>
            <RoundingAmount>0.50</RoundingAmount>
            <ReducedTaxRateTax>0.00</ReducedTaxRateTax>
            <BaseTaxRateTax>787.50</BaseTaxRateTax>
            <TotalWithTaxCurr>0.00</TotalWithTaxCurr>
            <TaxPointDate>2019-01-15</TaxPointDate>
            <DoubleEntryBookkeepingCode>0.000</DoubleEntryBookkeepingCode>
            <SingleEntryBookkeepingCode>0</SingleEntryBookkeepingCode>
            <SingleEntryBookkeepingSubCode>0</SingleEntryBookkeepingSubCode>
            <ControlStatement_Leasing>F</ControlStatement_Leasing>
            <TotalWeight>0.000000</TotalWeight>
            <CostCentre>03</CostCentre>
            <ContractNumber>0</ContractNumber>
            <VatRegime>0</VatRegime>
            <VatCountry>CZ</VatCountry>
            <EURExchangeRate>1.000000</EURExchangeRate>
            <EURExchangeRateAmount>1.000000</EURExchangeRateAmount>
            <CalcParams>UPDP=2;VATRU=0.10;VATRM=0;TRU=1.00;TRM=0;VATCA=1;VATCUPA=1;TRD=0;TRDCA=0;VATFRB=0</CalcParams>
            <VariableSymbol>2019002</VariableSymbol>
            <ConstantSymbol>0308</ConstantSymbol>
            <PaymentDueDate>2019-01-29</PaymentDueDate>
            <CurrRateAmount>1.000000</CurrRateAmount>
            <CurrRate>1.000000</CurrRate>
            <PaidAmount>0.00</PaidAmount>
            <PaidAmountCurr>0.00</PaidAmountCurr>
            <InvoiceType>F</InvoiceType>
            <PaymentMeansCode>převodem</PaymentMeansCode>
            <DeliveryTypeCode>poštou</DeliveryTypeCode>
            <Discount>0.00</Discount>
            <Company>
                <CompanyId>55555551</CompanyId>
                <Name>Vodovody, a.s.</Name>
                <Street>Pražská 11</Street>
                <City>Praha 1</City>
                <Country>Česká republika</Country>
                <CountryCode>CZ</CountryCode>
                <ZipCode>11000</ZipCode>
                <VatNumber>CZ55555551</VatNumber>
                <NaturalPerson>F</NaturalPerson>
            </Company>
            <Items>
                <Item>
                    <Description>Úklidové práce</Description>
                    <RowType>1</RowType>
                    <TaxCode>41</TaxCode>
                    <UnitCode>hod</UnitCode>
                    <Quantity>25.000000</Quantity>
                    <UnitPrice>150.000000</UnitPrice>
                    <TaxPercent>21.00</TaxPercent>
                    <TaxAmount>31.500000</TaxAmount>
                    <DiscountPercent>0.00</DiscountPercent>
                    <UnitDiscount>0.000000</UnitDiscount>
                    <StockCardNumber>0.00</StockCardNumber>
                    <CostCentre>03</CostCentre>
                    <ContractNumber>0</ContractNumber>
                    <RowSumType>1</RowSumType>
                    <TotalWeight>0.000000</TotalWeight>
                </Item>
                <Item>
                    <Description>.</Description>
                    <RowType>1</RowType>
                    <TaxCode>41</TaxCode>
                    <Quantity>0.000000</Quantity>
                    <UnitPrice>0.000000</UnitPrice>
                    <TaxPercent>0.00</TaxPercent>
                    <TaxAmount>0.000000</TaxAmount>
                    <DiscountPercent>0.00</DiscountPercent>
                    <UnitDiscount>0.000000</UnitDiscount>
                    <StockCardNumber>0.00</StockCardNumber>
                    <CostCentre>03</CostCentre>
                    <ContractNumber>0</ContractNumber>
                    <RowSumType>1</RowSumType>
                    <TotalWeight>0.000000</TotalWeight>
                </Item>
                <Item>
                    <Description>.</Description>
                    <RowType>1</RowType>
                    <TaxCode>41</TaxCode>
                    <Quantity>0.000000</Quantity>
                    <UnitPrice>0.000000</UnitPrice>
                    <TaxPercent>0.00</TaxPercent>
                    <TaxAmount>0.000000</TaxAmount>
                    <DiscountPercent>0.00</DiscountPercent>
                    <UnitDiscount>0.000000</UnitDiscount>
                    <StockCardNumber>0.00</StockCardNumber>
                    <CostCentre>03</CostCentre>
                    <ContractNumber>0</ContractNumber>
                    <RowSumType>1</RowSumType>
                    <TotalWeight>0.000000</TotalWeight>
                </Item>
                <Item>
                    <Description>-----  Tuzemská faktura ------</Description>
                    <RowType>1</RowType>
                    <TaxCode>41</TaxCode>
                    <Quantity>0.000000</Quantity>
                    <UnitPrice>0.000000</UnitPrice>
                    <TaxPercent>0.00</TaxPercent>
                    <TaxAmount>0.000000</TaxAmount>
                    <DiscountPercent>0.00</DiscountPercent>
                    <UnitDiscount>0.000000</UnitDiscount>
                    <StockCardNumber>0.00</StockCardNumber>
                    <CostCentre>03</CostCentre>
                    <ContractNumber>0</ContractNumber>
                    <RowSumType>1</RowSumType>
                    <TotalWeight>0.000000</TotalWeight>
                </Item>
            </Items>
            <SumValues>
                <SumValue>
                    <TaxCode>41</TaxCode>
                    <TaxType>1</TaxType>
                    <TaxPercent>21.00</TaxPercent>
                    <CurrencyCode>CZK</CurrencyCode>
                    <Amount>3750.00</Amount>
                    <Tax>787.50</Tax>
                    <TaxCurrRateAmount>0.00</TaxCurrRateAmount>
                    <TaxCurrRateTax>0.00</TaxCurrRateTax>
                    <ReverseChargeAmount>0.00</ReverseChargeAmount>
                    <ReverseChargeTax>0.00</ReverseChargeTax>
                    <TaxCurrRateReverseChargeAmount>0.00</TaxCurrRateReverseChargeAmount>
                    <TaxCurrRateReverseChargeTax>0.00</TaxCurrRateReverseChargeTax>
                    <TaxApplied>0.00</TaxApplied>
                </SumValue>
                <SumValue>
                    <TaxCode>41</TaxCode>
                    <TaxType>3</TaxType>
                    <TaxPercent>0.00</TaxPercent>
                    <CurrencyCode>CZK</CurrencyCode>
                    <Amount>0.00</Amount>
                    <Tax>0.00</Tax>
                    <TaxCurrRateAmount>0.00</TaxCurrRateAmount>
                    <TaxCurrRateTax>0.00</TaxCurrRateTax>
                    <ReverseChargeAmount>0.00</ReverseChargeAmount>
                    <ReverseChargeTax>0.00</ReverseChargeTax>
                    <TaxCurrRateReverseChargeAmount>0.00</TaxCurrRateReverseChargeAmount>
                    <TaxCurrRateReverseChargeTax>0.00</TaxCurrRateReverseChargeTax>
                    <TaxApplied>0.00</TaxApplied>
                </SumValue>
                <SumValue>
                    <TaxCode>41</TaxCode>
                    <TaxType>4</TaxType>
                    <TaxPercent>99.00</TaxPercent>
                    <CurrencyCode>CZK</CurrencyCode>
                    <Amount>0.50</Amount>
                    <Tax>0.00</Tax>
                    <TaxCurrRateAmount>0.00</TaxCurrRateAmount>
                    <TaxCurrRateTax>0.00</TaxCurrRateTax>
                    <ReverseChargeAmount>0.00</ReverseChargeAmount>
                    <ReverseChargeTax>0.00</ReverseChargeTax>
                    <TaxCurrRateReverseChargeAmount>0.00</TaxCurrRateReverseChargeAmount>
                    <TaxCurrRateReverseChargeTax>0.00</TaxCurrRateReverseChargeTax>
                    <TaxApplied>0.00</TaxApplied>
                </SumValue>
            </SumValues>
        </Invoice>
        <Invoice>
            <DocumentNumber>2019003</DocumentNumber>
            <IssueDate>2019-01-15</IssueDate>
            <CurrencyCode>CZK</CurrencyCode>
            <ValuesWithTax>F</ValuesWithTax>
            <TaxCode>41</TaxCode>
            <ZeroTaxRateAmount>0.00</ZeroTaxRateAmount>
            <ReducedTaxRateAmount>0.00</ReducedTaxRateAmount>
            <BaseTaxRateAmount>5500.00</BaseTaxRateAmount>
            <RoundingAmount>0.00</RoundingAmount>
            <ReducedTaxRateTax>0.00</ReducedTaxRateTax>
            <BaseTaxRateTax>1155.00</BaseTaxRateTax>
            <TotalWithTaxCurr>0.00</TotalWithTaxCurr>
            <TaxPointDate>2019-01-15</TaxPointDate>
            <DoubleEntryBookkeepingCode>0.000</DoubleEntryBookkeepingCode>
            <SingleEntryBookkeepingCode>0</SingleEntryBookkeepingCode>
            <SingleEntryBookkeepingSubCode>0</SingleEntryBookkeepingSubCode>
            <ControlStatement_Leasing>F</ControlStatement_Leasing>
            <TotalWeight>25.000000</TotalWeight>
            <CostCentre>03</CostCentre>
            <ContractNumber>0</ContractNumber>
            <VatRegime>0</VatRegime>
            <VatCountry>CZ</VatCountry>
            <EURExchangeRate>1.000000</EURExchangeRate>
            <EURExchangeRateAmount>1.000000</EURExchangeRateAmount>
            <CalcParams>UPDP=2;VATRU=0.10;VATRM=0;TRU=1.00;TRM=0;VATCA=1;VATCUPA=1;TRD=0;TRDCA=0;VATFRB=0</CalcParams>
            <VariableSymbol>2019003</VariableSymbol>
            <ConstantSymbol>0308</ConstantSymbol>
            <PaymentDueDate>2019-01-29</PaymentDueDate>
            <CurrRateAmount>1.000000</CurrRateAmount>
            <CurrRate>1.000000</CurrRate>
            <PaidAmount>6655.00</PaidAmount>
            <PaidAmountCurr>6655.00</PaidAmountCurr>
            <InvoiceType>F</InvoiceType>
            <DeliveryNoteID>V190002</DeliveryNoteID>
            <PaymentMeansCode>převodem</PaymentMeansCode>
            <DeliveryTypeCode>poštou</DeliveryTypeCode>
            <Discount>0.00</Discount>
            <Company>
                <CompanyId>99999997</CompanyId>
                <Name>Zdeněk Novák</Name>
                <Street>Náměstí 1</Street>
                <City>Zlín</City>
                <Country>Česká republika</Country>
                <CountryCode>CZ</CountryCode>
                <ZipCode>76001</ZipCode>
                <VatNumber>CZ62352415</VatNumber>
                <Email>mail@mail.cz</Email>
                <NaturalPerson>T</NaturalPerson>
            </Company>
            <Items>
                <Item>
                    <Description>1,00 stůl dřevěný</Description>
                    <RowType>1</RowType>
                    <TaxCode>41</TaxCode>
                    <UnitCode>ks</UnitCode>
                    <Quantity>1.000000</Quantity>
                    <UnitPrice>5500.000000</UnitPrice>
                    <TaxPercent>21.00</TaxPercent>
                    <TaxAmount>1155.000000</TaxAmount>
                    <DiscountPercent>0.00</DiscountPercent>
                    <UnitDiscount>0.000000</UnitDiscount>
                    <StockCardNumber>1.00</StockCardNumber>
                    <CostCentre>03</CostCentre>
                    <ContractNumber>0</ContractNumber>
                    <RowSumType>1</RowSumType>
                    <TotalWeight>25.000000</TotalWeight>
                </Item>
                <Item>
                    <Description>.</Description>
                    <RowType>1</RowType>
                    <TaxCode>41</TaxCode>
                    <Quantity>0.000000</Quantity>
                    <UnitPrice>0.000000</UnitPrice>
                    <TaxPercent>0.00</TaxPercent>
                    <TaxAmount>0.000000</TaxAmount>
                    <DiscountPercent>0.00</DiscountPercent>
                    <UnitDiscount>0.000000</UnitDiscount>
                    <StockCardNumber>0.00</StockCardNumber>
                    <CostCentre>03</CostCentre>
                    <ContractNumber>0</ContractNumber>
                    <RowSumType>1</RowSumType>
                    <TotalWeight>0.000000</TotalWeight>
                </Item>
                <Item>
                    <Description>.</Description>
                    <RowType>1</RowType>
                    <TaxCode>41</TaxCode>
                    <Quantity>0.000000</Quantity>
                    <UnitPrice>0.000000</UnitPrice>
                    <TaxPercent>0.00</TaxPercent>
                    <TaxAmount>0.000000</TaxAmount>
                    <DiscountPercent>0.00</DiscountPercent>
                    <UnitDiscount>0.000000</UnitDiscount>
                    <StockCardNumber>0.00</StockCardNumber>
                    <CostCentre>03</CostCentre>
                    <ContractNumber>0</ContractNumber>
                    <RowSumType>1</RowSumType>
                    <TotalWeight>0.000000</TotalWeight>
                </Item>
                <Item>
                    <Description>------- Tuzemská faktura -----</Description>
                    <RowType>1</RowType>
                    <TaxCode>41</TaxCode>
                    <Quantity>0.000000</Quantity>
                    <UnitPrice>0.000000</UnitPrice>
                    <TaxPercent>0.00</TaxPercent>
                    <TaxAmount>0.000000</TaxAmount>
                    <DiscountPercent>0.00</DiscountPercent>
                    <UnitDiscount>0.000000</UnitDiscount>
                    <StockCardNumber>0.00</StockCardNumber>
                    <CostCentre>03</CostCentre>
                    <ContractNumber>0</ContractNumber>
                    <RowSumType>1</RowSumType>
                    <TotalWeight>0.000000</TotalWeight>
                </Item>
            </Items>
            <SumValues>
                <SumValue>
                    <TaxCode>41</TaxCode>
                    <TaxType>1</TaxType>
                    <TaxPercent>21.00</TaxPercent>
                    <CurrencyCode>CZK</CurrencyCode>
                    <Amount>5500.00</Amount>
                    <Tax>1155.00</Tax>
                    <TaxCurrRateAmount>0.00</TaxCurrRateAmount>
                    <TaxCurrRateTax>0.00</TaxCurrRateTax>
                    <ReverseChargeAmount>0.00</ReverseChargeAmount>
                    <ReverseChargeTax>0.00</ReverseChargeTax>
                    <TaxCurrRateReverseChargeAmount>0.00</TaxCurrRateReverseChargeAmount>
                    <TaxCurrRateReverseChargeTax>0.00</TaxCurrRateReverseChargeTax>
                    <TaxApplied>0.00</TaxApplied>
                </SumValue>
                <SumValue>
                    <TaxCode>41</TaxCode>
                    <TaxType>3</TaxType>
                    <TaxPercent>0.00</TaxPercent>
                    <CurrencyCode>CZK</CurrencyCode>
                    <Amount>0.00</Amount>
                    <Tax>0.00</Tax>
                    <TaxCurrRateAmount>0.00</TaxCurrRateAmount>
                    <TaxCurrRateTax>0.00</TaxCurrRateTax>
                    <ReverseChargeAmount>0.00</ReverseChargeAmount>
                    <ReverseChargeTax>0.00</ReverseChargeTax>
                    <TaxCurrRateReverseChargeAmount>0.00</TaxCurrRateReverseChargeAmount>
                    <TaxCurrRateReverseChargeTax>0.00</TaxCurrRateReverseChargeTax>
                    <TaxApplied>0.00</TaxApplied>
                </SumValue>
            </SumValues>
            <Payments>
                <Payment>
                    <PaymentType>4</PaymentType>
                    <PaymentDate>2019-02-06</PaymentDate>
                    <DocumentNumber>ZAP00001</DocumentNumber>
                    <Amount>6655.00</Amount>
                    <AmountCurr>6655.00</AmountCurr>
                    <AmountPaidDocumentCurr>6655.00</AmountPaidDocumentCurr>
                    <CurrencyCode>CZK</CurrencyCode>
                    <CurrRate>1.000000</CurrRate>
                    <CurrRateAmount>1.000000</CurrRateAmount>
                </Payment>
            </Payments>
        </Invoice>
        <Invoice>
            <DocumentNumber>2019004</DocumentNumber>
            <IssueDate>2019-01-16</IssueDate>
            <CurrencyCode>CZK</CurrencyCode>
            <ValuesWithTax>F</ValuesWithTax>
            <TaxCode>41</TaxCode>
            <DocType>D</DocType>
            <ZeroTaxRateAmount>0.00</ZeroTaxRateAmount>
            <ReducedTaxRateAmount>0.00</ReducedTaxRateAmount>
            <BaseTaxRateAmount>-5500.00</BaseTaxRateAmount>
            <RoundingAmount>0.00</RoundingAmount>
            <ReducedTaxRateTax>0.00</ReducedTaxRateTax>
            <BaseTaxRateTax>-1155.00</BaseTaxRateTax>
            <TotalWithTaxCurr>0.00</TotalWithTaxCurr>
            <TaxPointDate>2019-01-23</TaxPointDate>
            <DoubleEntryBookkeepingCode>0.000</DoubleEntryBookkeepingCode>
            <SingleEntryBookkeepingCode>0</SingleEntryBookkeepingCode>
            <SingleEntryBookkeepingSubCode>0</SingleEntryBookkeepingSubCode>
            <ControlStatement_Leasing>F</ControlStatement_Leasing>
            <TotalWeight>25.000000</TotalWeight>
            <CostCentre>03</CostCentre>
            <ContractNumber>0</ContractNumber>
            <VatRegime>0</VatRegime>
            <VatCountry>CZ</VatCountry>
            <EURExchangeRate>1.000000</EURExchangeRate>
            <EURExchangeRateAmount>1.000000</EURExchangeRateAmount>
            <CalcParams>UPDP=2;VATRU=0.10;VATRM=0;TRU=1.00;TRM=0;VATCA=1;VATCUPA=1;TRD=0;TRDCA=0;VATFRB=0</CalcParams>
            <VariableSymbol>2019004</VariableSymbol>
            <ConstantSymbol>0308</ConstantSymbol>
            <PaymentDueDate>2019-01-30</PaymentDueDate>
            <CurrRateAmount>1.000000</CurrRateAmount>
            <CurrRate>1.000000</CurrRate>
            <PaidAmount>-6655.00</PaidAmount>
            <PaidAmountCurr>-6655.00</PaidAmountCurr>
            <InvoiceType>F</InvoiceType>
            <DeliveryNoteID>V190002</DeliveryNoteID>
            <PaymentMeansCode>převodem</PaymentMeansCode>
            <DeliveryTypeCode>poštou</DeliveryTypeCode>
            <Discount>0.00</Discount>
            <Company>
                <CompanyId>99999997</CompanyId>
                <Name>Zdeněk Novák</Name>
                <Street>Náměstí 1</Street>
                <City>Zlín</City>
                <Country>Česká republika</Country>
                <CountryCode>CZ</CountryCode>
                <ZipCode>76001</ZipCode>
                <VatNumber>CZ62352415</VatNumber>
                <Email>mail@mail.cz</Email>
                <NaturalPerson>T</NaturalPerson>
            </Company>
            <Items>
                <Item>
                    <Description>Dobropis k faktuře č. 2019003</Description>
                    <RowType>2</RowType>
                    <TaxCode>0</TaxCode>
                    <Quantity>0.000000</Quantity>
                    <UnitPrice>0.000000</UnitPrice>
                    <TaxPercent>0.00</TaxPercent>
                    <TaxAmount>0.000000</TaxAmount>
                    <DiscountPercent>0.00</DiscountPercent>
                    <UnitDiscount>0.000000</UnitDiscount>
                    <StockCardNumber>0.00</StockCardNumber>
                    <CostCentre>03</CostCentre>
                    <ContractNumber>0</ContractNumber>
                    <RowSumType>1</RowSumType>
                    <TotalWeight>0.000000</TotalWeight>
                </Item>
                <Item>
                    <Description>ze dne 15.01.2019</Description>
                    <RowType>2</RowType>
                    <TaxCode>0</TaxCode>
                    <Quantity>0.000000</Quantity>
                    <UnitPrice>0.000000</UnitPrice>
                    <TaxPercent>0.00</TaxPercent>
                    <TaxAmount>0.000000</TaxAmount>
                    <DiscountPercent>0.00</DiscountPercent>
                    <UnitDiscount>0.000000</UnitDiscount>
                    <StockCardNumber>0.00</StockCardNumber>
                    <CostCentre>03</CostCentre>
                    <ContractNumber>0</ContractNumber>
                    <RowSumType>1</RowSumType>
                    <TotalWeight>0.000000</TotalWeight>
                </Item>
                <Item>
                    <Description>1,00 stůl dřevěný</Description>
                    <RowType>1</RowType>
                    <TaxCode>41</TaxCode>
                    <UnitCode>ks</UnitCode>
                    <Quantity>1.000000</Quantity>
                    <UnitPrice>-5500.000000</UnitPrice>
                    <TaxPercent>21.00</TaxPercent>
                    <TaxAmount>-1155.000000</TaxAmount>
                    <DiscountPercent>0.00</DiscountPercent>
                    <UnitDiscount>0.000000</UnitDiscount>
                    <StockCardNumber>1.00</StockCardNumber>
                    <CostCentre>03</CostCentre>
                    <ContractNumber>0</ContractNumber>
                    <RowSumType>1</RowSumType>
                    <TotalWeight>25.000000</TotalWeight>
                </Item>
                <Item>
                    <Description>.</Description>
                    <RowType>1</RowType>
                    <TaxCode>41</TaxCode>
                    <Quantity>0.000000</Quantity>
                    <UnitPrice>0.000000</UnitPrice>
                    <TaxPercent>0.00</TaxPercent>
                    <TaxAmount>0.000000</TaxAmount>
                    <DiscountPercent>0.00</DiscountPercent>
                    <UnitDiscount>0.000000</UnitDiscount>
                    <StockCardNumber>0.00</StockCardNumber>
                    <CostCentre>03</CostCentre>
                    <ContractNumber>0</ContractNumber>
                    <RowSumType>1</RowSumType>
                    <TotalWeight>0.000000</TotalWeight>
                </Item>
                <Item>
                    <Description>.</Description>
                    <RowType>1</RowType>
                    <TaxCode>41</TaxCode>
                    <Quantity>0.000000</Quantity>
                    <UnitPrice>0.000000</UnitPrice>
                    <TaxPercent>0.00</TaxPercent>
                    <TaxAmount>0.000000</TaxAmount>
                    <DiscountPercent>0.00</DiscountPercent>
                    <UnitDiscount>0.000000</UnitDiscount>
                    <StockCardNumber>0.00</StockCardNumber>
                    <CostCentre>03</CostCentre>
                    <ContractNumber>0</ContractNumber>
                    <RowSumType>1</RowSumType>
                    <TotalWeight>0.000000</TotalWeight>
                </Item>
                <Item>
                    <Description>--- Opravný daňový doklad - Dobropis -----</Description>
                    <RowType>1</RowType>
                    <TaxCode>41</TaxCode>
                    <Quantity>0.000000</Quantity>
                    <UnitPrice>0.000000</UnitPrice>
                    <TaxPercent>0.00</TaxPercent>
                    <TaxAmount>0.000000</TaxAmount>
                    <DiscountPercent>0.00</DiscountPercent>
                    <UnitDiscount>0.000000</UnitDiscount>
                    <StockCardNumber>0.00</StockCardNumber>
                    <CostCentre>03</CostCentre>
                    <ContractNumber>0</ContractNumber>
                    <RowSumType>1</RowSumType>
                    <TotalWeight>0.000000</TotalWeight>
                </Item>
            </Items>
            <SumValues>
                <SumValue>
                    <TaxCode>41</TaxCode>
                    <TaxType>1</TaxType>
                    <TaxPercent>21.00</TaxPercent>
                    <CurrencyCode>CZK</CurrencyCode>
                    <Amount>-5500.00</Amount>
                    <Tax>-1155.00</Tax>
                    <TaxCurrRateAmount>0.00</TaxCurrRateAmount>
                    <TaxCurrRateTax>0.00</TaxCurrRateTax>
                    <ReverseChargeAmount>0.00</ReverseChargeAmount>
                    <ReverseChargeTax>0.00</ReverseChargeTax>
                    <TaxCurrRateReverseChargeAmount>0.00</TaxCurrRateReverseChargeAmount>
                    <TaxCurrRateReverseChargeTax>0.00</TaxCurrRateReverseChargeTax>
                    <TaxApplied>0.00</TaxApplied>
                </SumValue>
                <SumValue>
                    <TaxCode>41</TaxCode>
                    <TaxType>3</TaxType>
                    <TaxPercent>0.00</TaxPercent>
                    <CurrencyCode>CZK</CurrencyCode>
                    <Amount>0.00</Amount>
                    <Tax>0.00</Tax>
                    <TaxCurrRateAmount>0.00</TaxCurrRateAmount>
                    <TaxCurrRateTax>0.00</TaxCurrRateTax>
                    <ReverseChargeAmount>0.00</ReverseChargeAmount>
                    <ReverseChargeTax>0.00</ReverseChargeTax>
                    <TaxCurrRateReverseChargeAmount>0.00</TaxCurrRateReverseChargeAmount>
                    <TaxCurrRateReverseChargeTax>0.00</TaxCurrRateReverseChargeTax>
                    <TaxApplied>0.00</TaxApplied>
                </SumValue>
            </SumValues>
            <Payments>
                <Payment>
                    <PaymentType>4</PaymentType>
                    <PaymentDate>2019-02-06</PaymentDate>
                    <DocumentNumber>ZAP00001</DocumentNumber>
                    <Amount>-6655.00</Amount>
                    <AmountCurr>-6655.00</AmountCurr>
                    <AmountPaidDocumentCurr>-6655.00</AmountPaidDocumentCurr>
                    <CurrencyCode>CZK</CurrencyCode>
                    <CurrRate>1.000000</CurrRate>
                    <CurrRateAmount>1.000000</CurrRateAmount>
                </Payment>
            </Payments>
        </Invoice>
        <Invoice>
            <DocumentNumber>2019005</DocumentNumber>
            <IssueDate>2019-01-16</IssueDate>
            <CurrencyCode>CZK</CurrencyCode>
            <ValuesWithTax>F</ValuesWithTax>
            <TaxCode>43</TaxCode>
            <ZeroTaxRateAmount>1100.00</ZeroTaxRateAmount>
            <ReducedTaxRateAmount>0.00</ReducedTaxRateAmount>
            <BaseTaxRateAmount>0.00</BaseTaxRateAmount>
            <RoundingAmount>0.00</RoundingAmount>
            <ReducedTaxRateTax>0.00</ReducedTaxRateTax>
            <BaseTaxRateTax>0.00</BaseTaxRateTax>
            <TotalWithTaxCurr>0.00</TotalWithTaxCurr>
            <TaxPointDate>2019-01-16</TaxPointDate>
            <DoubleEntryBookkeepingCode>0.000</DoubleEntryBookkeepingCode>
            <SingleEntryBookkeepingCode>0</SingleEntryBookkeepingCode>
            <SingleEntryBookkeepingSubCode>0</SingleEntryBookkeepingSubCode>
            <ControlStatement_Leasing>F</ControlStatement_Leasing>
            <TotalWeight>5.000000</TotalWeight>
            <CostCentre>03</CostCentre>
            <ContractNumber>0</ContractNumber>
            <VatRegime>0</VatRegime>
            <VatCountry>CZ</VatCountry>
            <EURExchangeRate>1.000000</EURExchangeRate>
            <EURExchangeRateAmount>1.000000</EURExchangeRateAmount>
            <CalcParams>UPDP=2;VATRU=0.10;VATRM=0;TRU=1.00;TRM=0;VATCA=1;VATCUPA=1;TRD=0;TRDCA=0;VATFRB=0</CalcParams>
            <VariableSymbol>2019005</VariableSymbol>
            <ConstantSymbol>0308</ConstantSymbol>
            <PaymentDueDate>2019-01-30</PaymentDueDate>
            <CurrRateAmount>1.000000</CurrRateAmount>
            <CurrRate>1.000000</CurrRate>
            <PaidAmount>0.00</PaidAmount>
            <PaidAmountCurr>0.00</PaidAmountCurr>
            <InvoiceType>F</InvoiceType>
            <DeliveryNoteID>V190003</DeliveryNoteID>
            <PaymentMeansCode>převodem</PaymentMeansCode>
            <DeliveryTypeCode>poštou</DeliveryTypeCode>
            <RecapitulativeStatementCode>0</RecapitulativeStatementCode>
            <Discount>0.00</Discount>
            <Company>
                <CompanyId>88848884</CompanyId>
                <Name>Trading GmbH</Name>
                <Street>Straße 1</Street>
                <City>Hamburg</City>
                <Country>Německo</Country>
                <CountryCode>DE</CountryCode>
                <ZipCode>20001</ZipCode>
                <VatNumber>DE00001</VatNumber>
                <Email>mail@mail.cz</Email>
                <Note>zahraniční partner - faktura vždy v EUR</Note>
                <NaturalPerson>F</NaturalPerson>
            </Company>
            <Items>
                <Item>
                    <Description>2,00 olej na dřevo</Description>
                    <RowType>1</RowType>
                    <TaxCode>43</TaxCode>
                    <ItemType>Z</ItemType>
                    <UnitCode>l</UnitCode>
                    <Quantity>5.000000</Quantity>
                    <UnitPrice>220.000000</UnitPrice>
                    <TaxPercent>0.00</TaxPercent>
                    <TaxAmount>0.000000</TaxAmount>
                    <DiscountPercent>0.00</DiscountPercent>
                    <UnitDiscount>0.000000</UnitDiscount>
                    <StockCardNumber>2.00</StockCardNumber>
                    <CostCentre>03</CostCentre>
                    <ContractNumber>0</ContractNumber>
                    <RowSumType>1</RowSumType>
                    <TotalWeight>1.000000</TotalWeight>
                </Item>
                <Item>
                    <Description>.</Description>
                    <RowType>1</RowType>
                    <TaxCode>43</TaxCode>
                    <Quantity>0.000000</Quantity>
                    <UnitPrice>0.000000</UnitPrice>
                    <TaxPercent>0.00</TaxPercent>
                    <TaxAmount>0.000000</TaxAmount>
                    <DiscountPercent>0.00</DiscountPercent>
                    <UnitDiscount>0.000000</UnitDiscount>
                    <StockCardNumber>0.00</StockCardNumber>
                    <CostCentre>03</CostCentre>
                    <ContractNumber>0</ContractNumber>
                    <RowSumType>1</RowSumType>
                    <TotalWeight>0.000000</TotalWeight>
                </Item>
                <Item>
                    <Description>-----  Faktura do EU -----</Description>
                    <RowType>1</RowType>
                    <TaxCode>43</TaxCode>
                    <Quantity>0.000000</Quantity>
                    <UnitPrice>0.000000</UnitPrice>
                    <TaxPercent>0.00</TaxPercent>
                    <TaxAmount>0.000000</TaxAmount>
                    <DiscountPercent>0.00</DiscountPercent>
                    <UnitDiscount>0.000000</UnitDiscount>
                    <StockCardNumber>0.00</StockCardNumber>
                    <CostCentre>03</CostCentre>
                    <ContractNumber>0</ContractNumber>
                    <RowSumType>1</RowSumType>
                    <TotalWeight>0.000000</TotalWeight>
                </Item>
            </Items>
            <SumValues>
                <SumValue>
                    <TaxCode>43</TaxCode>
                    <TaxType>3</TaxType>
                    <TaxPercent>0.00</TaxPercent>
                    <CurrencyCode>CZK</CurrencyCode>
                    <Amount>1100.00</Amount>
                    <Tax>0.00</Tax>
                    <TaxCurrRateAmount>0.00</TaxCurrRateAmount>
                    <TaxCurrRateTax>0.00</TaxCurrRateTax>
                    <ReverseChargeAmount>0.00</ReverseChargeAmount>
                    <ReverseChargeTax>0.00</ReverseChargeTax>
                    <TaxCurrRateReverseChargeAmount>0.00</TaxCurrRateReverseChargeAmount>
                    <TaxCurrRateReverseChargeTax>0.00</TaxCurrRateReverseChargeTax>
                    <TaxApplied>0.00</TaxApplied>
                </SumValue>
            </SumValues>
        </Invoice>
        <Invoice>
            <DocumentNumber>2019006</DocumentNumber>
            <IssueDate>2019-01-15</IssueDate>
            <CurrencyCode>CZK</CurrencyCode>
            <ValuesWithTax>F</ValuesWithTax>
            <TaxCode>41</TaxCode>
            <ZeroTaxRateAmount>0.00</ZeroTaxRateAmount>
            <ReducedTaxRateAmount>0.00</ReducedTaxRateAmount>
            <BaseTaxRateAmount>30000.00</BaseTaxRateAmount>
            <RoundingAmount>0.00</RoundingAmount>
            <ReducedTaxRateTax>0.00</ReducedTaxRateTax>
            <BaseTaxRateTax>6300.00</BaseTaxRateTax>
            <TotalWithTaxCurr>0.00</TotalWithTaxCurr>
            <TaxPointDate>2019-01-15</TaxPointDate>
            <DoubleEntryBookkeepingCode>0.000</DoubleEntryBookkeepingCode>
            <SingleEntryBookkeepingCode>0</SingleEntryBookkeepingCode>
            <SingleEntryBookkeepingSubCode>0</SingleEntryBookkeepingSubCode>
            <ControlStatement_Leasing>F</ControlStatement_Leasing>
            <TotalWeight>0.000000</TotalWeight>
            <CostCentre>03</CostCentre>
            <ContractNumber>0</ContractNumber>
            <VatRegime>0</VatRegime>
            <VatCountry>CZ</VatCountry>
            <EURExchangeRate>1.000000</EURExchangeRate>
            <EURExchangeRateAmount>1.000000</EURExchangeRateAmount>
            <CalcParams>UPDP=2;VATRU=0.10;VATRM=0;TRU=1.00;TRM=0;VATCA=1;VATCUPA=1;TRD=0;TRDCA=0;VATFRB=0</CalcParams>
            <VariableSymbol>2019006</VariableSymbol>
            <ConstantSymbol>0308</ConstantSymbol>
            <PaymentDueDate>2019-01-25</PaymentDueDate>
            <CurrRateAmount>1.000000</CurrRateAmount>
            <CurrRate>1.000000</CurrRate>
            <PaidAmount>36300.00</PaidAmount>
            <PaidAmountCurr>36300.00</PaidAmountCurr>
            <InvoiceType>F</InvoiceType>
            <DeliveryNoteID>2019006</DeliveryNoteID>
            <ProformaInvoiceID>55001</ProformaInvoiceID>
            <PaymentMeansCode>převodem</PaymentMeansCode>
            <PaymentInvoiceID>55001</PaymentInvoiceID>
            <Discount>0.00</Discount>
            <Company>
                <CompanyId>99999995</CompanyId>
                <Name>Dlouhá Eliška</Name>
                <Street>Náchodská 1</Street>
                <City>Praha 9</City>
                <Country>Česká republika</Country>
                <CountryCode>CZ</CountryCode>
                <ZipCode>19300</ZipCode>
                <VatNumber>CZ99999995</VatNumber>
                <Email>mail@mail.cz</Email>
                <NaturalPerson>T</NaturalPerson>
            </Company>
            <Items>
                <Item>
                    <Description>Pronájem reklamní plochy</Description>
                    <RowType>1</RowType>
                    <TaxCode>41</TaxCode>
                    <ItemType>Z</ItemType>
                    <UnitCode>měs</UnitCode>
                    <Quantity>3.000000</Quantity>
                    <UnitPrice>10000.000000</UnitPrice>
                    <TaxPercent>21.00</TaxPercent>
                    <TaxAmount>2100.000000</TaxAmount>
                    <DiscountPercent>0.00</DiscountPercent>
                    <UnitDiscount>0.000000</UnitDiscount>
                    <StockCardNumber>0.00</StockCardNumber>
                    <CostCentre>03</CostCentre>
                    <ContractNumber>0</ContractNumber>
                    <RowSumType>1</RowSumType>
                    <TotalWeight>0.000000</TotalWeight>
                </Item>
                <Item>
                    <Description>1/2019 - 3/2019</Description>
                    <RowType>1</RowType>
                    <TaxCode>41</TaxCode>
                    <ItemType>Z</ItemType>
                    <Quantity>0.000000</Quantity>
                    <UnitPrice>0.000000</UnitPrice>
                    <TaxPercent>0.00</TaxPercent>
                    <TaxAmount>0.000000</TaxAmount>
                    <DiscountPercent>0.00</DiscountPercent>
                    <UnitDiscount>0.000000</UnitDiscount>
                    <StockCardNumber>0.00</StockCardNumber>
                    <CostCentre>03</CostCentre>
                    <ContractNumber>0</ContractNumber>
                    <RowSumType>1</RowSumType>
                    <TotalWeight>0.000000</TotalWeight>
                </Item>
                <Item>
                    <Description>.</Description>
                    <RowType>1</RowType>
                    <TaxCode>41</TaxCode>
                    <ItemType>Z</ItemType>
                    <Quantity>0.000000</Quantity>
                    <UnitPrice>0.000000</UnitPrice>
                    <TaxPercent>0.00</TaxPercent>
                    <TaxAmount>0.000000</TaxAmount>
                    <DiscountPercent>0.00</DiscountPercent>
                    <UnitDiscount>0.000000</UnitDiscount>
                    <StockCardNumber>0.00</StockCardNumber>
                    <CostCentre>03</CostCentre>
                    <ContractNumber>0</ContractNumber>
                    <RowSumType>1</RowSumType>
                    <TotalWeight>0.000000</TotalWeight>
                </Item>
                <Item>
                    <Description>------ Faktura z předfaktury -----</Description>
                    <RowType>1</RowType>
                    <TaxCode>41</TaxCode>
                    <ItemType>Z</ItemType>
                    <Quantity>0.000000</Quantity>
                    <UnitPrice>0.000000</UnitPrice>
                    <TaxPercent>0.00</TaxPercent>
                    <TaxAmount>0.000000</TaxAmount>
                    <DiscountPercent>0.00</DiscountPercent>
                    <UnitDiscount>0.000000</UnitDiscount>
                    <StockCardNumber>0.00</StockCardNumber>
                    <CostCentre>03</CostCentre>
                    <ContractNumber>0</ContractNumber>
                    <RowSumType>1</RowSumType>
                    <TotalWeight>0.000000</TotalWeight>
                </Item>
            </Items>
            <SumValues>
                <SumValue>
                    <TaxCode>41</TaxCode>
                    <TaxType>1</TaxType>
                    <TaxPercent>21.00</TaxPercent>
                    <CurrencyCode>CZK</CurrencyCode>
                    <Amount>30000.00</Amount>
                    <Tax>6300.00</Tax>
                    <TaxCurrRateAmount>0.00</TaxCurrRateAmount>
                    <TaxCurrRateTax>0.00</TaxCurrRateTax>
                    <ReverseChargeAmount>0.00</ReverseChargeAmount>
                    <ReverseChargeTax>0.00</ReverseChargeTax>
                    <TaxCurrRateReverseChargeAmount>0.00</TaxCurrRateReverseChargeAmount>
                    <TaxCurrRateReverseChargeTax>0.00</TaxCurrRateReverseChargeTax>
                    <TaxApplied>0.00</TaxApplied>
                </SumValue>
                <SumValue>
                    <TaxCode>41</TaxCode>
                    <TaxType>3</TaxType>
                    <TaxPercent>0.00</TaxPercent>
                    <CurrencyCode>CZK</CurrencyCode>
                    <Amount>0.00</Amount>
                    <Tax>0.00</Tax>
                    <TaxCurrRateAmount>0.00</TaxCurrRateAmount>
                    <TaxCurrRateTax>0.00</TaxCurrRateTax>
                    <ReverseChargeAmount>0.00</ReverseChargeAmount>
                    <ReverseChargeTax>0.00</ReverseChargeTax>
                    <TaxCurrRateReverseChargeAmount>0.00</TaxCurrRateReverseChargeAmount>
                    <TaxCurrRateReverseChargeTax>0.00</TaxCurrRateReverseChargeTax>
                    <TaxApplied>0.00</TaxApplied>
                </SumValue>
            </SumValues>
            <Payments>
                <Payment>
                    <PaymentType>1</PaymentType>
                    <PaymentDate>2019-01-15</PaymentDate>
                    <DocumentNumber>BV1900001</DocumentNumber>
                    <Amount>36300.00</Amount>
                    <AmountCurr>36300.00</AmountCurr>
                    <AmountPaidDocumentCurr>36300.00</AmountPaidDocumentCurr>
                    <CurrencyCode>CZK</CurrencyCode>
                    <CurrRate>1.000000</CurrRate>
                    <CurrRateAmount>1.000000</CurrRateAmount>
                </Payment>
            </Payments>
        </Invoice>
        <Invoice>
            <DocumentNumber>55001</DocumentNumber>
            <IssueDate>2019-01-10</IssueDate>
            <CurrencyCode>CZK</CurrencyCode>
            <ValuesWithTax>F</ValuesWithTax>
            <TaxCode>19</TaxCode>
            <ZeroTaxRateAmount>0.00</ZeroTaxRateAmount>
            <ReducedTaxRateAmount>0.00</ReducedTaxRateAmount>
            <BaseTaxRateAmount>30000.00</BaseTaxRateAmount>
            <RoundingAmount>0.00</RoundingAmount>
            <ReducedTaxRateTax>0.00</ReducedTaxRateTax>
            <BaseTaxRateTax>6300.00</BaseTaxRateTax>
            <TotalWithTaxCurr>0.00</TotalWithTaxCurr>
            <DoubleEntryBookkeepingCode>0.000</DoubleEntryBookkeepingCode>
            <SingleEntryBookkeepingCode>0</SingleEntryBookkeepingCode>
            <SingleEntryBookkeepingSubCode>0</SingleEntryBookkeepingSubCode>
            <ControlStatement_Leasing>F</ControlStatement_Leasing>
            <TotalWeight>0.000000</TotalWeight>
            <CostCentre>03</CostCentre>
            <ContractNumber>0</ContractNumber>
            <VatRegime>0</VatRegime>
            <VatCountry>CZ</VatCountry>
            <EURExchangeRate>1.000000</EURExchangeRate>
            <EURExchangeRateAmount>1.000000</EURExchangeRateAmount>
            <CalcParams>UPDP=2;VATRU=0.10;VATRM=0;TRU=1.00;TRM=0;VATCA=1;VATCUPA=1;TRD=0;TRDCA=0;VATFRB=0</CalcParams>
            <VariableSymbol>55001</VariableSymbol>
            <ConstantSymbol>0308</ConstantSymbol>
            <PaymentDueDate>2019-01-20</PaymentDueDate>
            <CurrRateAmount>1.000000</CurrRateAmount>
            <CurrRate>1.000000</CurrRate>
            <PaidAmount>36300.00</PaidAmount>
            <PaidAmountCurr>0.00</PaidAmountCurr>
            <InvoiceType>X</InvoiceType>
            <ProformaInvoiceID>2019006</ProformaInvoiceID>
            <PaymentMeansCode>převodem</PaymentMeansCode>
            <PaymentInvoiceID>2019006</PaymentInvoiceID>
            <Discount>0.00</Discount>
            <Company>
                <CompanyId>99999995</CompanyId>
                <Name>Dlouhá Eliška</Name>
                <Street>Náchodská 1</Street>
                <City>Praha 9</City>
                <Country>Česká republika</Country>
                <CountryCode>CZ</CountryCode>
                <ZipCode>19300</ZipCode>
                <VatNumber>CZ99999995</VatNumber>
                <Email>mail@mail.cz</Email>
                <NaturalPerson>T</NaturalPerson>
            </Company>
            <Items>
                <Item>
                    <Description>Pronájem reklamní plochy</Description>
                    <RowType>1</RowType>
                    <TaxCode>19</TaxCode>
                    <ItemType>Z</ItemType>
                    <UnitCode>měs</UnitCode>
                    <Quantity>3.000000</Quantity>
                    <UnitPrice>10000.000000</UnitPrice>
                    <TaxPercent>21.00</TaxPercent>
                    <TaxAmount>2100.000000</TaxAmount>
                    <DiscountPercent>0.00</DiscountPercent>
                    <UnitDiscount>0.000000</UnitDiscount>
                    <StockCardNumber>0.00</StockCardNumber>
                    <CostCentre>03</CostCentre>
                    <ContractNumber>0</ContractNumber>
                    <RowSumType>1</RowSumType>
                    <TotalWeight>0.000000</TotalWeight>
                </Item>
                <Item>
                    <Description>1/2019 - 3/2019</Description>
                    <RowType>1</RowType>
                    <TaxCode>19</TaxCode>
                    <ItemType>Z</ItemType>
                    <Quantity>0.000000</Quantity>
                    <UnitPrice>0.000000</UnitPrice>
                    <TaxPercent>0.00</TaxPercent>
                    <TaxAmount>0.000000</TaxAmount>
                    <DiscountPercent>0.00</DiscountPercent>
                    <UnitDiscount>0.000000</UnitDiscount>
                    <StockCardNumber>0.00</StockCardNumber>
                    <CostCentre>03</CostCentre>
                    <ContractNumber>0</ContractNumber>
                    <RowSumType>1</RowSumType>
                    <TotalWeight>0.000000</TotalWeight>
                </Item>
                <Item>
                    <Description>.</Description>
                    <RowType>1</RowType>
                    <TaxCode>19</TaxCode>
                    <ItemType>Z</ItemType>
                    <Quantity>0.000000</Quantity>
                    <UnitPrice>0.000000</UnitPrice>
                    <TaxPercent>0.00</TaxPercent>
                    <TaxAmount>0.000000</TaxAmount>
                    <DiscountPercent>0.00</DiscountPercent>
                    <UnitDiscount>0.000000</UnitDiscount>
                    <StockCardNumber>0.00</StockCardNumber>
                    <CostCentre>03</CostCentre>
                    <ContractNumber>0</ContractNumber>
                    <RowSumType>1</RowSumType>
                    <TotalWeight>0.000000</TotalWeight>
                </Item>
                <Item>
                    <Description>------ Předfaktura -----</Description>
                    <RowType>1</RowType>
                    <TaxCode>19</TaxCode>
                    <ItemType>Z</ItemType>
                    <Quantity>0.000000</Quantity>
                    <UnitPrice>0.000000</UnitPrice>
                    <TaxPercent>0.00</TaxPercent>
                    <TaxAmount>0.000000</TaxAmount>
                    <DiscountPercent>0.00</DiscountPercent>
                    <UnitDiscount>0.000000</UnitDiscount>
                    <StockCardNumber>0.00</StockCardNumber>
                    <CostCentre>03</CostCentre>
                    <ContractNumber>0</ContractNumber>
                    <RowSumType>1</RowSumType>
                    <TotalWeight>0.000000</TotalWeight>
                </Item>
            </Items>
            <SumValues>
                <SumValue>
                    <TaxCode>19</TaxCode>
                    <TaxType>1</TaxType>
                    <TaxPercent>21.00</TaxPercent>
                    <CurrencyCode>CZK</CurrencyCode>
                    <Amount>30000.00</Amount>
                    <Tax>6300.00</Tax>
                    <TaxCurrRateAmount>0.00</TaxCurrRateAmount>
                    <TaxCurrRateTax>0.00</TaxCurrRateTax>
                    <ReverseChargeAmount>0.00</ReverseChargeAmount>
                    <ReverseChargeTax>0.00</ReverseChargeTax>
                    <TaxCurrRateReverseChargeAmount>0.00</TaxCurrRateReverseChargeAmount>
                    <TaxCurrRateReverseChargeTax>0.00</TaxCurrRateReverseChargeTax>
                    <TaxApplied>0.00</TaxApplied>
                </SumValue>
                <SumValue>
                    <TaxCode>19</TaxCode>
                    <TaxType>3</TaxType>
                    <TaxPercent>0.00</TaxPercent>
                    <CurrencyCode>CZK</CurrencyCode>
                    <Amount>0.00</Amount>
                    <Tax>0.00</Tax>
                    <TaxCurrRateAmount>0.00</TaxCurrRateAmount>
                    <TaxCurrRateTax>0.00</TaxCurrRateTax>
                    <ReverseChargeAmount>0.00</ReverseChargeAmount>
                    <ReverseChargeTax>0.00</ReverseChargeTax>
                    <TaxCurrRateReverseChargeAmount>0.00</TaxCurrRateReverseChargeAmount>
                    <TaxCurrRateReverseChargeTax>0.00</TaxCurrRateReverseChargeTax>
                    <TaxApplied>0.00</TaxApplied>
                </SumValue>
            </SumValues>
        </Invoice>
    </IssuedInvoices>
</MRPKSData>
